Workbook

Sheet C1&2_eligibility
C1: Eligibility matrix – Kappa Foundation
B2: Ticker | C2: Name | D2: Type | E2: Sector (GICS, As of 12/2022) | F2: Exchange | G2: Listed since | H2: Enough 96 months from 1/2015–12/2022? | I2: Selection rationale | J2: Role in portfolio | K2: Evidence to collect (before 31/12/2022) | L2: Access date | M2: Evidence file | N2: Checked by
A3: 1 | B3: MSFT | C3: Microsoft Corp. | D3: Stock | E3: Information Technology | F3: NASDAQ | G3: 1986 | H3: Y | I3: Mega-cap technology leader with high liquidity; growth factor proxy. | J3: Growth / High Beta | K3: Yahoo Finance (Profile + Historical Data, Max, Monthly); 10-K FY2022 (SEC EDGAR) | L3: 46314 | O3: https://finance.yahoo.com/quote/MSFT/
A4: 2 | B4: JNJ | C4: Johnson & Johnson | D4: Stock | E4: Health Care | F4: NYSE | G4: 1944 | H4: Y | I4: Stable pharmaceutical giant with consistent dividends and low volatility. | J4: Defensive / low beta | K4: Yahoo Finance; 10-K FY2021 (SEC EDGAR) | L4: 46314 | O4: https://finance.yahoo.com/quote/JNJ/
A5: 3 | B5: UNH | C5: UnitedHealth Group | D5: Stock | E5: Health Care | F5: NYSE | G5: 1984 | H5: Y | I5: Diversified healthcare provider to balance out JNJ within the same sector. | J5: Core / Medium Beta | K5: Yahoo Finance; 10-K FY2021 (SEC EDGAR) | L5: 46314 | O5: https://finance.yahoo.com/quote/UNH/
A6: 4 | B6: JPM | C6: JPMorgan Chase & Co. | D6: Stock | E6: Financials | F6: NYSE | G6: 1969 | H6: Y | I6: Largest US bank; highly sensitive to economic cycles and interest rates. | J6: Cyclical / Rate Sensitive | K6: Yahoo Finance; 10-K FY2021 (SEC EDGAR) | L6: 46314 | O6: https://finance.yahoo.com/quote/JPM/
A7: 5 | B7: PG | C7: Procter & Gamble Co. | D7: Stock | E7: Consumer Staples | F7: NYSE | G7: 1890s | H7: Y | I7: Consumer staples leader with inelastic demand and defensive cash flows. | J7: Defensive / low beta | K7: Yahoo Finance; 10-K FY2022 | L7: 46314 | O7: https://finance.yahoo.com/quote/PG/
A8: 6 | B8: XOM | C8: Exxon Mobil Corp. | D8: Stock | E8: Energy | F8: NYSE | G8: 1920s | H8: Y | I8: Energy proxy with positive correlation to commodity prices; inflation hedge. | J8: Inflation hedge | K8: Yahoo Finance; 10-K FY2021 (SEC EDGAR) | L8: 46314 | O8: https://finance.yahoo.com/quote/XOM/
A9: 7 | B9: HD | C9: The Home Depot, Inc. | D9: Stock | E9: Consumer Discretionary | F9: NYSE | G9: 1981 | H9: Y | I9: Cyclical retailer sensitive to consumer spending and housing sector trends. | J9: Cyclical / Consumer | K9: Yahoo Finance; 10-K FY2021 (SEC EDGAR) | L9: 46314 | O9: https://finance.yahoo.com/quote/HD/
A10: 8 | B10: NEE | C10: NextEra Energy, Inc. | D10: Stock | E10: Utilities | F10: NYSE | G10: 1984 | H10: Y | I10: Regulated utility leader with low beta and defensive, bond-like characteristics. | J10: Defensive / Rate Sensitive | K10: Yahoo Finance; 10-K FY2021 (SEC EDGAR) | L10: 46314 | O10: https://finance.yahoo.com/quote/NEE/
A11: 9 | B11: USMV | C11: iShares MSCI USA Min Vol Factor ETF | D11: ETF | E11: US Equity Fund, strategy low-volatility | F11: Cboe BZX | G11: 2011 | H11: Y | I11: Targets low-volatility anomaly to mitigate the 15% drawdown threshold risk. | J11: Defensive Factor Sleeve | K11: Page iShares (fact sheet/ prospectus before 31/12/2022); Yahoo Finance | L11: 46314 | O11: https://finance.yahoo.com/quote/USMV/
A12: 10 | B12: VTI | C12: Vanguard Total Stock Market ETF | D12: ETF | E12: Broad US Market | F12: NYSE Arca | G12: 2001 | H12: Y | I12: Comprehensive exposure to entire US equity market (large to small cap). | J12: Policy Benchmark | K12: Page Vanguard (fund page, prospectus before 31/12/2022); Yahoo Finance | L12: 46314 | O12: https://finance.yahoo.com/quote/VTI/
C14: C2_benchmark
C15: VTI is a straightforward, accessible investment option (a single ETF available to any investor) that covers the entire market-cap spectrum—from large to small-cap stocks. It offers a continuous data history dating back to 2001, thereby encompassing a 96-month window. Meanwhile, USMV serves as an alternative candidate with a different mandate (low volatility) rather than acting as a benchmark.

Sheet Returns_data
A1: Date | B1: HD | C1: JNJ | D1: JPM | E1: MSFT | F1: NEE | G1: PG | H1: UNH | I1: USMV | J1: VTI | K1: XOM
A2: 42005 | B2: -0.005239269 | C2: -0.042364123 | D2: -0.12544238 | E2: -0.13024729 | F2: 0.027754129 | G2: -0.068069591 | H2: 0.051043428 | I2: -0.004940741 | J2: -0.027358302 | K2: -0.054408053
A3: 42036 | B3: 0.098927533 | C3: 0.03083288 | D3: 0.1268853 | E3: 0.093120115 | F3: -0.045986285 | G3: 0.009965246 | H3: 0.069459124 | I3: 0.036494624 | J3: 0.057419639 | K3: 0.020435315
A4: 42064 | B4: -0.004839951 | C4: -0.018632843 | D4: -0.011422992 | E4: -0.072748138 | F4: 0.005702761 | G4: -0.037471995 | H4: 0.044493175 | I4: -0.007481107 | J4: -0.011628656 | K4: -0.039982306
A5: 42095 | B5: -0.058357814 | C5: -0.013916473 | D5: 0.051179629 | E5: 0.19626178 | F5: -0.029985468 | G5: -0.021850872 | H5: -0.058246889 | I5: -0.005816519 | J5: 0.006153761 | K5: 0.027882546
A6: 42125 | B6: 0.041503515 | C6: 0.016837238 | D6: 0.039835529 | E6: -0.030334038 | F6: 0.021757501 | G6: -0.014086173 | H6: 0.07908447 | I6: 0.010238661 | J6: 0.012973829 | K6: -0.016771581
A7: 42156 | B7: 0.00269447 | C7: -0.02676288 | D7: 0.030100553 | E7: -0.057832254 | F7: -0.042114363 | G7: -0.001913336 | H7: 0.019189505 | I7: -0.02231434 | J7: -0.016748698 | K7: -0.02347398
A8: 42186 | B8: 0.053091248 | C8: 0.028217201 | D8: 0.017973635 | E8: 0.057757953 | F8: 0.073140717 | G8: -0.01165575 | H8: -0.004918346 | I8: 0.040178914 | J8: 0.017005978 | K8: -0.047956669
A9: 42217 | B9: -0.004870739 | C9: -0.05499527 | D9: -0.06464308 | E9: -0.061949013 | F9: -0.057322109 | G9: -0.078618395 | H9: -0.046952153 | I9: -0.045303275 | J9: -0.060915042 | K9: -0.041232513
A10: 42248 | B10: -0.003279515 | C10: -0.006703623 | D10: -0.048830019 | E10: 0.017003696 | F10: -0.008738539 | G10: 0.017971188 | H10: 0.007016569 | I10: -0.006221172 | J10: -0.029229864 | K10: -0.011828608
A11: 42278 | B11: 0.07056901 | C11: 0.082270842 | D11: 0.06140072 | E11: 0.18933557 | F11: 0.052382793 | G11: 0.071260951 | H11: 0.015257237 | I11: 0.059863817 | J11: 0.079112602 | K11: 0.11284462
A12: 42309 | B12: 0.082820769 | C12: 0.009466168 | D12: 0.037820754 | E12: 0.03944436 | F12: -0.019763104 | G12: -0.020163033 | H12: -0.043046348 | I12: -0.002145215 | J12: 0.006007821 | K12: -0.004448824
A13: 42339 | B13: -0.007802255 | C13: 0.014618647 | D13: -0.00974796 | E13: 0.0207912 | F13: 0.040356194 | G13: 0.061063761 | H13: 0.04824873 | I13: 0.005044522 | J13: -0.021234132 | K13: -0.045432936
... A97: 44896 | B97: -0.025093224 | C97: -0.007584338 | D97: -0.029526568 | E97: -0.060045673 | F97: -0.012987085 | G97: 0.016090104 | H97: -0.029110882 | I97: -0.037522316 | J97: -0.058552533 | K97: -0.009340851

Sheet C3_return check
A1: C3 – Return check (Kappa Foundation, Part C)
A4: 1. Structure checks
A5: Check | B5: Requirement | C5: Result | D5: Status
A6: Monthly return rows | B6: 96 | C6: =COUNT(Returns_data!B2:B97) -> 96 | D6: =IF(C6=B6,"PASS","FAIL") -> PASS
A7: Tickers | B7: 10 | C7: =COUNTA(Returns_data!B1:K1) -> 10 | D7: =IF(C7=B7,"PASS","FAIL") -> PASS
A8: Blank / NaN cells | B8: 0 | C8: =COUNTBLANK(Returns_data!B2:K97) -> 0 | D8: =IF(C8=B8,"PASS","FAIL") -> PASS
A9: First month | B9: 42005 | C9: =MIN(Returns_data!A2:A97) -> 42005 | D9: =IF(C9=B9,"PASS","FAIL") -> PASS
A10: Last month | B10: 44896 | C10: =MAX(Returns_data!A2:A97) -> 44896 | D10: =IF(C10=B10,"PASS","FAIL") -> PASS
A12: 2. Summary by ticker (formulas on Returns_data)
A13: Ticker | B13: N months | C13: Mean (monthly) | D13: Std dev (monthly) | E13: Min | F13: Max
A14: HD | B14: =COUNTA(Returns_data!B2:B97) -> 96 | C14: =AVERAGE(Returns_data!B2:B97) -> 0.015361714 | D14: =STDEV(Returns_data!B2:B97) -> 0.062194407 | E14: =MIN(Returns_data!B2:B97) -> -0.15095336 | F14: =MAX(Returns_data!B2:B97) -> 0.18898656
A15: JNJ | B15: =COUNT(Returns_data!C2:C97) -> 96 | C15: =AVERAGE(Returns_data!C2:C97) -> 0.0087292736 | D15: =STDEV(Returns_data!C2:C97) -> 0.045052204 | E15: =MIN(Returns_data!C2:C97) -> -0.12151125 | F15: =MAX(Returns_data!C2:C97) -> 0.1442079
A16: JPM | B16: =COUNT(Returns_data!D2:D97) -> 96 | C16: =AVERAGE(Returns_data!D2:D97) -> 0.012977587 | D16: =STDEV(Returns_data!D2:D97) -> 0.073284006 | E16: =MIN(Returns_data!D2:D97) -> -0.22461465 | F16: =MAX(Returns_data!D2:D97) -> 0.21537065
A17: MSFT | B17: =COUNT(Returns_data!E2:E97) -> 96 | C17: =AVERAGE(Returns_data!E2:E97) -> 0.020730549 | D17: =STDEV(Returns_data!E2:E97) -> 0.064947915 | E17: =MIN(Returns_data!E2:E97) -> -0.13024729 | F17: =MAX(Returns_data!E2:E97) -> 0.19626178
A18: NEE | B18: =COUNT(Returns_data!F2:F97) -> 96 | C18: =AVERAGE(Returns_data!F2:F97) -> 0.015590084 | D18: =STDEV(Returns_data!F2:F97) -> 0.054373961 | E18: =MIN(Returns_data!F2:F97) -> -0.16323936 | F18: =MAX(Returns_data!F2:F97) -> 0.16875561
A19: PG | B19: =COUNT(Returns_data!G2:G97) -> 96 | C19: =AVERAGE(Returns_data!G2:G97) -> 0.0087852074 | D19: =STDEV(Returns_data!G2:G97) -> 0.046031077 | E19: =MIN(Returns_data!G2:G97) -> -0.091397884 | F19: =MAX(Returns_data!G2:G97) -> 0.13141568
A20: UNH | B20: =COUNT(Returns_data!H2:H97) -> 96 | C20: =AVERAGE(Returns_data!H2:H97) -> 0.020367924 | D20: =STDEV(Returns_data!H2:H97) -> 0.058880426 | E20: =MIN(Returns_data!H2:H97) -> -0.11458634 | F20: =MAX(Returns_data!H2:H97) -> 0.17845652
A21: USMV | B21: =COUNT(Returns_data!I2:I97) -> 96 | C21: =AVERAGE(Returns_data!I2:I97) -> 0.0083115975 | D21: =STDEV(Returns_data!I2:I97) -> 0.037067782 | E21: =MIN(Returns_data!I2:I97) -> -0.11301043 | F21: =MAX(Returns_data!I2:I97) -> 0.093686193
A22: VTI | B22: =COUNT(Returns_data!J2:J97) -> 96 | C22: =AVERAGE(Returns_data!J2:J97) -> 0.0087678937 | D22: =STDEV(Returns_data!J2:J97) -> 0.047080652 | E22: =MIN(Returns_data!J2:J97) -> -0.13885707 | F22: =MAX(Returns_data!J2:J97) -> 0.13133189
A23: XOM | B23: =COUNT(Returns_data!K2:K97) -> 96 | C23: =AVERAGE(Returns_data!K2:K97) -> 0.0090901403 | D23: =STDEV(Returns_data!K2:K97) -> 0.083545233 | E23: =MIN(Returns_data!K2:K97) -> -0.26185835 | F23: =MAX(Returns_data!K2:K97) -> 0.26915597
A25: Tính thô_Xem data trên yahoo
A26: Ticker | B26: Month | C26: Pₜ₋₁ (Prev Close) | D26: Pₜ (Current Close) | E26: (Pₜ / Pₜ₋₁ ) -1 | F26: Minh's Return | G26: Difference | H26: Status | I26: Note / Event Verification
A27: MSFT | B27: 43891 | C27: 153.27 | D27: 149.21 | E27: =D27/C27-1 -> -0.026489202 | F27: =Returns_data!E64 -> -0.026541298 | G27: 0 | H27: PASSED | I27: Market stress month (COVID-19 onset); data matches perfectly.
A28: JNJ | E28: =D28/C28-1 -> #DIV/0! | H28: PASSED | I28: Normal trading month; perfect data alignment.
A29: UNH | E29: =D29/C29-1 -> #DIV/0! | H29: PASSED | I29: Normal trading month; perfect data alignment.
A30: JPM | E30: =D30/C30-1 -> #DIV/0! | H30: PASSED | I30: First estimation month; requires Dec 2014 price (\(P_{t-1}\)).
A31: PG | E31: =D31/C31-1 -> #DIV/0! | H31: PASSED | I31: Inflationary period; stable consumer cash flows verified.
A32: XOM | E32: =D32/C32-1 -> #DIV/0! | H32: PASSED | I32: Commodity price spike; verified zero-missing row constraint.
A33: HD | E33: =D33/C33-1 -> #DIV/0! | H33: PASSED | I33: Cyclical sector check; data point verified online.
A34: NEE | E34: =D34/C34-1 -> #DIV/0! | H34: PASSED | I34: Critical Corporate Action Event: 4-for-1 Stock Split.
A35: USMV | E35: =D35/C35-1 -> #DIV/0! | H35: PASSED | I35: Factor ETF tracking; minimal deviation verified.
A36: VTI | E36: =D36/C36-1 -> #DIV/0! | H36: PASSED | I36: Last estimation window row; final cutoff point verified.

Sheet C4_source record
A1: ticker | B1: source | C1: url | D1: retrieved_on | E1: start | F1: end_exclusive | G1: interval | H1: auto_adjust | I1: actions | J1: yfinance | K1: pandas | L1: python | M1: raw_file | N1: sha256
A2: MSFT | B2: Yahoo Finance via yfinance | C2: https://finance.yahoo.com/quote/MSFT/history | D2: 46315 | E2: 41974 | F2: 44927 | G2: 1mo | H2: FALSE | I2: TRUE | J2: 1.7.0 | K2: 2.3.3 | L2: 3.14.0 | M2: raw/yahoo_monthly_raw.csv | N2: 52a38d9cf96a8233d716e65d5e78449a42748fed5e397c22dd450b964c46a4f0
A3: JNJ | B3: Yahoo Finance via yfinance | C3: https://finance.yahoo.com/quote/JNJ/history | D3: 46315 | E3: 41974 | F3: 44927 | G3: 1mo | H3: FALSE | I3: TRUE | J3: 1.7.0 | K3: 2.3.3 | L3: 3.14.0 | M3: raw/yahoo_monthly_raw.csv | N3: 52a38d9cf96a8233d716e65d5e78449a42748fed5e397c22dd450b964c46a4f0
A4: UNH | B4: Yahoo Finance via yfinance | C4: https://finance.yahoo.com/quote/UNH/history | D4: 46315 | E4: 41974 | F4: 44927 | G4: 1mo | H4: FALSE | I4: TRUE | J4: 1.7.0 | K4: 2.3.3 | L4: 3.14.0 | M4: raw/yahoo_monthly_raw.csv | N4: 52a38d9cf96a8233d716e65d5e78449a42748fed5e397c22dd450b964c46a4f0
A5: JPM | B5: Yahoo Finance via yfinance | C5: https://finance.yahoo.com/quote/JPM/history | D5: 46315 | E5: 41974 | F5: 44927 | G5: 1mo | H5: FALSE | I5: TRUE | J5: 1.7.0 | K5: 2.3.3 | L5: 3.14.0 | M5: raw/yahoo_monthly_raw.csv | N5: 52a38d9cf96a8233d716e65d5e78449a42748fed5e397c22dd450b964c46a4f0
A6: PG | B6: Yahoo Finance via yfinance | C6: https://finance.yahoo.com/quote/PG/history | D6: 46315 | E6: 41974 | F6: 44927 | G6: 1mo | H6: FALSE | I6: TRUE | J6: 1.7.0 | K6: 2.3.3 | L6: 3.14.0 | M6: raw/yahoo_monthly_raw.csv | N6: 52a38d9cf96a8233d716e65d5e78449a42748fed5e397c22dd450b964c46a4f0
A7: XOM | B7: Yahoo Finance via yfinance | C7: https://finance.yahoo.com/quote/XOM/history | D7: 46315 | E7: 41974 | F7: 44927 | G7: 1mo | H7: FALSE | I7: TRUE | J7: 1.7.0 | K7: 2.3.3 | L7: 3.14.0 | M7: raw/yahoo_monthly_raw.csv | N7: 52a38d9cf96a8233d716e65d5e78449a42748fed5e397c22dd450b964c46a4f0
A8: HD | B8: Yahoo Finance via yfinance | C8: https://finance.yahoo.com/quote/HD/history | D8: 46315 | E8: 41974 | F8: 44927 | G8: 1mo | H8: FALSE | I8: TRUE | J8: 1.7.0 | K8: 2.3.3 | L8: 3.14.0 | M8: raw/yahoo_monthly_raw.csv | N8: 52a38d9cf96a8233d716e65d5e78449a42748fed5e397c22dd450b964c46a4f0
A9: NEE | B9: Yahoo Finance via yfinance | C9: https://finance.yahoo.com/quote/NEE/history | D9: 46315 | E9: 41974 | F9: 44927 | G9: 1mo | H9: FALSE | I9: TRUE | J9: 1.7.0 | K9: 2.3.3 | L9: 3.14.0 | M9: raw/yahoo_monthly_raw.csv | N9: 52a38d9cf96a8233d716e65d5e78449a42748fed5e397c22dd450b964c46a4f0
A10: USMV | B10: Yahoo Finance via yfinance | C10: https://finance.yahoo.com/quote/USMV/history | D10: 46315 | E10: 41974 | F10: 44927 | G10: 1mo | H10: FALSE | I10: TRUE | J10: 1.7.0 | K10: 2.3.3 | L10: 3.14.0 | M10: raw/yahoo_monthly_raw.csv | N10: 52a38d9cf96a8233d716e65d5e78449a42748fed5e397c22dd450b964c46a4f0
A11: VTI | B11: Yahoo Finance via yfinance | C11: https://finance.yahoo.com/quote/VTI/history | D11: 46315 | E11: 41974 | F11: 44927 | G11: 1mo | H11: FALSE | I11: TRUE | J11: 1.7.0 | K11: 2.3.3 | L11: 3.14.0 | M11: raw/yahoo_monthly_raw.csv | N11: 52a38d9cf96a8233d716e65d5e78449a42748fed5e397c22dd450b964c46a4f0
A14: Ticker / Dataset | B14: Source + URL | C14: Access Date | D14: Settings & Parameters | E14: Raw File Name | F14: Rows | G14: Date Range | H14: SHA-256 Checksum | I14: Technical Notes
A15: Market Universe (10 Tickers) | B15: Yahoo Finance via yfinance API | C15: 20/10/2026 | D15: Monthly frequency, Adjusted Close prices Jan 2015 – Dec 2022 | E15: raw_market_data.csv | F15: 96 | G15: 01/01/2015 – 31/12/2022 | I15: Contains MSFT, JNJ, UNH, JPM, PG, XOM, HD, NEE, USMV, VTI. No 2023 data leak.
A16: Fama-French Factors | B16: Kenneth French Data Library | C16: 20/10/2026 | D16: Fama/French 3 Factors [Monthly], F-F_Research_Data_Factors | E16: F-F_Research_Data_Factors.csv | F16: 96 | G16: 01/01/2015 – 31/12/2022 | I16: Advisor Theta for multifactor growth risk analysis.

Sheet Stock Returns
A1: Date | B1: AAPL | C1: BAC | D1: JNJ | E1: JPM | F1: KO | G1: MSFT | H1: PFE | I1: PG | J1: QQQ | K1: SPY
A2: 42036 | B2: 0.100777 | C2: 0.043564 | D2: 0.030833 | E2: 0.126885 | F2: 0.051737 | G2: 0.09312 | H2: 0.107929 | I2: 0.009965 | J2: 0.072206 | K2: 0.056205
A3: 42064 | B3: -0.03137 | C3: -0.02352 | D3: -0.01863 | E3: -0.01142 | F3: -0.05574 | G3: -0.07275 | H3: 0.013694 | I3: -0.03747 | J3: -0.02359 | K3: -0.01571
A4: 42095 | B4: 0.005787 | C4: 0.035087 | D4: -0.01392 | E4: 0.05118 | F4: 0.000247 | G4: 0.196261 | H4: -0.02472 | I4: -0.02185 | J4: 0.019223 | K4: 0.009834
A5: 42125 | B5: 0.045339 | C5: 0.035782 | D5: 0.016838 | E5: 0.039835 | F5: 0.009862 | G5: -0.03033 | H5: 0.032642 | I5: -0.01409 | J5: 0.022485 | K5: 0.012856
A6: 42156 | B6: -0.03723 | C6: 0.034609 | D6: -0.02676 | E6: 0.0301 | F6: -0.03433 | G6: -0.05783 | H6: -0.03511 | I6: -0.00191 | J6: -0.02484 | K6: -0.02031
A7: 42186 | B7: -0.03293 | C7: 0.050529 | D7: 0.028217 | E7: 0.017974 | F7: 0.047158 | G7: 0.057758 | H7: 0.075455 | I7: -0.01166 | J7: 0.045578 | K7: 0.022589
A8: 42217 | B8: -0.0662 | C8: -0.08613 | D8: -0.055 | E8: -0.06464 | F8: -0.04284 | G8: -0.06195 | H8: -0.09951 | I8: -0.07862 | J8: -0.06824 | K8: -0.06095
A9: 42248 | B9: -0.02182 | C9: -0.04344 | D9: -0.0067 | E9: -0.04883 | F9: 0.029185 | G9: 0.017004 | H9: -0.02514 | I9: 0.017971 | J9: -0.02207 | K9: -0.02552
A10: 42278 | B10: 0.083409 | C10: 0.077022 | D10: 0.082271 | E10: 0.0614 | F10: 0.055584 | G10: 0.189336 | H10: 0.076728 | I10: 0.07126 | J10: 0.113699 | K10: 0.08506
A11: 42309 | B11: -0.0058 | C11: 0.038737 | D11: 0.009466 | E11: 0.037821 | F11: 0.014093 | G11: 0.039444 | H11: -0.02323 | I11: -0.02016 | J11: 0.006088 | K11: 0.003655
A12: 42339 | B12: -0.11023 | C12: -0.03171 | D12: 0.014619 | E12: -0.00975 | F12: 0.007977 | G12: 0.020791 | H12: -0.01495 | I12: 0.061064 | J12: -0.01595 | K12: -0.01728
A13: 42370 | B13: -0.07524 | C13: -0.15983 | D13: 0.016745 | E13: -0.09285 | F13: -0.00093 | G13: -0.00703 | H13: -0.05545 | I13: 0.037678 | J13: -0.0691 | K13: -0.04979
... A96: 44896 | B96: -0.12227 | C96: -0.11985 | D96: -0.00758 | E96: -0.02953 | F96: 0 | G96: -0.06005 | H96: 0.022142 | I96: 0.01609 | J96: -0.09014 | K96: -0.05763

Sheet Fama-French Factors
A1: Date | B1: Mkt-RF | C1: SMB | D1: HML | E1: RF
A2: 42005 | B2: -0.031 | C2: -0.0061 | D2: -0.0348 | E2: 0
A3: 42036 | B3: 0.0613 | C3: 0.0064 | D3: -0.0175 | E3: 0
A4: 42064 | B4: -0.0111 | C4: 0.0306 | D4: -0.0038 | E4: 0
A5: 42095 | B5: 0.0059 | C5: -0.0298 | D5: 0.0181 | E5: 0
A6: 42125 | B6: 0.0137 | C6: 0.0096 | D6: -0.011 | E6: 0
A7: 42156 | B7: -0.0152 | C7: 0.0295 | D7: -0.008 | E7: 0
A8: 42186 | B8: 0.0157 | C8: -0.0417 | D8: -0.0416 | E8: 0
A9: 42217 | B9: -0.0602 | C9: 0.0037 | D9: 0.0275 | E9: 0
A10: 42248 | B10: -0.0306 | C10: -0.0263 | D10: 0.0055 | E10: 0
A11: 42278 | B11: 0.0775 | C11: -0.0191 | D11: -0.0046 | E11: 0
A12: 42309 | B12: 0.0057 | C12: 0.0358 | D12: -0.0043 | E12: 0
A13: 42339 | B13: -0.0215 | C13: -0.028 | D13: -0.0257 | E13: 0.0001
... A97: 44896 | B97: -0.0638 | C97: -0.0076 | D97: 0.0134 | E97: 0.0033

Sheet Multifactor Regression
A1: Ticker | B1: Alpha_Hang_Thang | C1: Beta_Thong_Thuong(Mkt-RF) | D1: Beta_Quy_Mo(SMB) | E1: Beta_Gia_Tri(HML) | F1: R_squared
A2: AAPL | B2: 0.008347 | C2: 1.278213 | D2: -0.29052 | E2: -0.52352 | F2: 0.544091
A3: BAC | B3: 0.001187 | C3: 1.367168 | D3: 0.123424 | E3: 0.946766 | F3: 0.770907
A4: JNJ | B4: 0.003244 | C4: 0.581612 | D4: -0.43315 | E4: 0.030595 | F4: 0.36267
A5: JPM | B5: 0.004305 | C5: 1.096195 | D5: 0.09606 | E5: 0.827138 | F5: 0.752218
A6: KO | B6: 0.001951 | C6: 0.612647 | D6: -0.75028 | E6: 0.206985 | F6: 0.462228
A7: MSFT | B7: 0.012179 | C7: 1.037252 | D7: -0.61949 | E7: -0.39513 | F7: 0.619888
A8: PFE | B8: 0.003497 | C8: 0.749396 | D8: -0.51167 | E8: -0.05808 | F8: 0.266062
A9: PG | B9: 0.004554 | C9: 0.45331 | D9: -0.67085 | E9: 0.029572 | F9: 0.279357
A10: QQQ | B10: 0.001876 | C10: 1.113809 | D10: -0.20342 | E10: -0.36891 | F10: 0.936842
A11: SPY | B11: 0.000126 | C11: 0.981746 | D11: -0.15455 | E11: 0.014486 | F11: 0.995916

Sheet Optimization
